pywui/__init__.py
pywui/api.py
pywui/app.py
pywui/decorator.py
pywui/di.py
pywui/dispatcher.py
pywui/pywui.png
pywui/window.py
pywui-0.1.7.dist-info/LICENSE
pywui-0.1.7.dist-info/METADATA
pywui-0.1.7.dist-info/WHEEL
pywui-0.1.7.dist-info/RECORD
