Metadata-Version: 2.1
Name: pywui
Version: 0.1.7
Summary: Pywui is a Python package wrapper for pywebview to make easy the communication between python and JS and async support.
Keywords: pywui,pywebview,pyinstaller,tauri,vite
Author: Tsiresy Milà
Author-email: tsiresymila@gmail.com
Requires-Python: >=3.10,<4.0
Classifier: Programming Language :: Python :: 3
Classifier: Programming Language :: Python :: 3.10
Classifier: Programming Language :: Python :: 3.11
Classifier: Programming Language :: Python :: 3.12
Requires-Dist: ujson (>=5.10.0,<6.0.0)
Requires-Dist: watchfiles (>=0.24.0,<0.25.0)
